grem-0.1.0.dist-info/METADATA
grem-0.1.0.dist-info/WHEEL
grem-0.1.0.dist-info/entry_points.txt
grem-0.1.0.dist-info/licenses/LICENSE
grem/__about__.py
grem/__init__.py
grem/__main__.py
grem-0.1.0.dist-info/RECORD
